LICENSE
MANIFEST.in
README.txt
pyproject.toml
setup.cfg
setup.py
src/TurboOptimizer.cpp
src/TurboOptimizer.hpp
src/spde.cpp
src/spde.pyx
src/SPDE.egg-info/PKG-INFO
src/SPDE.egg-info/SOURCES.txt
src/SPDE.egg-info/dependency_links.txt
src/SPDE.egg-info/not-zip-safe
src/SPDE.egg-info/top_level.txt